cv_tasks_lib-1.0.0.dist-info/licenses/LICENSE
cvlib/__init__.py
cvlib/__main__.py
cvlib/display.py
cvlib/tasks.py
cv_tasks_lib-1.0.0.dist-info/METADATA
cv_tasks_lib-1.0.0.dist-info/WHEEL
cv_tasks_lib-1.0.0.dist-info/top_level.txt
cv_tasks_lib-1.0.0.dist-info/RECORD
