Metadata-Version: 2.4
Name: cv_tasks_lib
Version: 1.0.0
Summary: Computer Vision Library - Display source code for 9 CV tasks
Author: CV Tasks
License: MIT
Project-URL: Homepage, https://example.com/cv_tasks
Project-URL: Documentation, https://example.com/cv_tasks/docs
Project-URL: Repository, https://example.com/cv_tasks/repo
Keywords: computer-vision,opencv,image-processing,education
Classifier: Programming Language :: Python :: 3
Classifier: Programming Language :: Python :: 3.7
Classifier: Programming Language :: Python :: 3.8
Classifier: Programming Language :: Python :: 3.9
Classifier: Programming Language :: Python :: 3.10
Classifier: Programming Language :: Python :: 3.11
Classifier: License :: OSI Approved :: MIT License
Classifier: Operating System :: OS Independent
Classifier: Intended Audience :: Education
Classifier: Topic :: Education
Classifier: Topic :: Multimedia :: Graphics
Requires-Python: >=3.7
License-File: LICENSE
Requires-Dist: opencv-python>=4.5.0
Requires-Dist: numpy>=1.19.0
Requires-Dist: matplotlib>=3.3.0
Requires-Dist: scikit-image>=0.18.0
Requires-Dist: scikit-learn>=0.24.0
Dynamic: license-file
Dynamic: requires-python
